{
  "permalink": "/blog/project-vision",
  "editUrl": "https://github.com/kubestellar/kubestellar/edit/main/kdemo/blog/2026-02-10-project-vision.md",
  "source": "@site/blog/2026-02-10-project-vision.md",
  "title": "Project Vision: From Zero to Multi-Cluster in 30 Minutes",
  "description": "The Problem",
  "date": "2026-02-10T00:00:00.000Z",
  "tags": [
    {
      "inline": true,
      "label": "lfx",
      "permalink": "/blog/tags/lfx"
    },
    {
      "inline": true,
      "label": "documentation",
      "permalink": "/blog/tags/documentation"
    },
    {
      "inline": true,
      "label": "onboarding",
      "permalink": "/blog/tags/onboarding"
    },
    {
      "inline": true,
      "label": "kubestellar",
      "permalink": "/blog/tags/kubestellar"
    }
  ],
  "readingTime": 1.13,
  "hasTruncateMarker": true,
  "authors": [
    {
      "name": "KubeStellar Community",
      "title": "CNCF Sandbox — Multi-cluster configuration management",
      "url": "https://github.com/kubestellar/kubestellar",
      "imageURL": "/img/logo.svg",
      "key": "kubestellar",
      "page": null
    }
  ],
  "frontMatter": {
    "slug": "project-vision",
    "title": "Project Vision: From Zero to Multi-Cluster in 30 Minutes",
    "authors": [
      "kubestellar"
    ],
    "tags": [
      "lfx",
      "documentation",
      "onboarding",
      "kubestellar"
    ]
  },
  "unlisted": false,
  "prevItem": {
    "title": "Mentorship Opportunity: Build the Future of KubeStellar Onboarding",
    "permalink": "/blog/mentorship-opportunity"
  }
}